torchbayesian/__init__.py
torchbayesian/bnn/__init__.py
torchbayesian/bnn/modules/__init__.py
torchbayesian/bnn/modules/bayesian_module.py
torchbayesian/bnn/priors/__init__.py
torchbayesian/bnn/priors/gaussian_prior.py
torchbayesian/bnn/priors/base/__init__.py
torchbayesian/bnn/priors/base/prior.py
torchbayesian/bnn/utils/__init__.py
torchbayesian/bnn/utils/factories.py
torchbayesian/bnn/utils/reparametrize.py
torchbayesian/bnn/variational_posteriors/__init__.py
torchbayesian/bnn/variational_posteriors/gaussian_posterior.py
torchbayesian/bnn/variational_posteriors/base/__init__.py
torchbayesian/bnn/variational_posteriors/base/variational_posterior.py
torchbayesian-0.1.0.dist-info/licenses/LICENSE
torchbayesian-0.1.0.dist-info/METADATA
torchbayesian-0.1.0.dist-info/WHEEL
torchbayesian-0.1.0.dist-info/top_level.txt
torchbayesian-0.1.0.dist-info/RECORD
