Metadata-Version: 2.4
Name: torchbayesian
Version: 0.1.0
Summary: One line to turn any PyTorch model into a BNN — effortless uncertainty quantification.
Author-email: Raphael Brodeur <raphael.brodeur@gmail.com>
License-Expression: Apache-2.0
Project-URL: Homepage, https://github.com/raphbrodeur/torchbayesian
Keywords: bayes-by-backprop,bayesian,bnn,deep-learning,neural-network,pytorch,torch,uncertainty
Classifier: Programming Language :: Python :: 3
Classifier: Operating System :: OS Independent
Classifier: Intended Audience :: Developers
Classifier: Intended Audience :: Financial and Insurance Industry
Classifier: Intended Audience :: Healthcare Industry
Classifier: Intended Audience :: Science/Research
Classifier: Topic :: Scientific/Engineering :: Artificial Intelligence
Requires-Python: >=3.10
License-File: LICENSE
Requires-Dist: torch>=1.10
Dynamic: license-file
